tingkart_api.py
tingkartapi-1.0.7.dist-info/METADATA
tingkartapi-1.0.7.dist-info/WHEEL
tingkartapi-1.0.7.dist-info/top_level.txt
tingkartapi-1.0.7.dist-info/RECORD
