Metadata-Version: 2.1
Name: tingkartapi
Version: 1.0.7
Summary: Tingkart api installation package
Home-page: https://github.com/577799/Tingkart_api
Author: Didrik Schønberg, Per Helge Litzheim Frøiland, Thomas Heggelund
Author-email: didrikfs@live.no
License: UNKNOWN
Platform: UNKNOWN
Classifier: Programming Language :: Python :: 3
Classifier: License :: OSI Approved :: MIT License
Classifier: Operating System :: OS Independent
Requires-Python: >=3.6
